imppkg/__init__.py
imppkg/data.json
imppkg/harmonic_mean.c
imppkg/harmonic_mean.cp310-win32.pyd
imppkg/harmonic_mean.pyx
imppkg/harmony.py
pubpypack_harmony_dane_hillard-0.0.2.dist-info/LICENSE
pubpypack_harmony_dane_hillard-0.0.2.dist-info/METADATA
pubpypack_harmony_dane_hillard-0.0.2.dist-info/WHEEL
pubpypack_harmony_dane_hillard-0.0.2.dist-info/entry_points.txt
pubpypack_harmony_dane_hillard-0.0.2.dist-info/top_level.txt
pubpypack_harmony_dane_hillard-0.0.2.dist-info/RECORD
